<?xml version="1.0" encoding="UTF-8"?>
<deploy
 date="2020.12.06.12:26:51"
 outputDirectory="/home/gtd/workspace/qts_prj/cnn/Mobilenet_FPGA_Accelarator_nios_ddr4/ip/init_para_rom/weight_rom/">
 <perimeter>
  <parameter
     name="AUTO_GENERATION_ID"
     type="Integer"
     defaultValue="0"
     onHdl="0"
     affectsHdl="1" />
  <parameter
     name="AUTO_UNIQUE_ID"
     type="String"
     defaultValue=""
     onHdl="0"
     affectsHdl="1" />
  <parameter
     name="AUTO_DEVICE_FAMILY"
     type="String"
     defaultValue="Arria 10"
     onHdl="0"
     affectsHdl="1" />
  <parameter
     name="AUTO_DEVICE"
     type="String"
     defaultValue="10AX066K3F40E2SG"
     onHdl="0"
     affectsHdl="1" />
  <parameter
     name="AUTO_DEVICE_SPEEDGRADE"
     type="String"
     defaultValue="2"
     onHdl="0"
     affectsHdl="1" />
  <parameter
     name="AUTO_CLOCK_CLOCK_RATE"
     type="Long"
     defaultValue="-1"
     onHdl="0"
     affectsHdl="1" />
  <parameter
     name="AUTO_CLOCK_CLOCK_DOMAIN"
     type="Integer"
     defaultValue="-1"
     onHdl="0"
     affectsHdl="1" />
  <parameter
     name="AUTO_CLOCK_RESET_DOMAIN"
     type="Integer"
     defaultValue="-1"
     onHdl="0"
     affectsHdl="1" />
  <interface name="q" kind="conduit" start="0">
   <property name="associatedClock" value="" />
   <property name="associatedReset" value="" />
   <property name="prSafe" value="false" />
   <port name="q" direction="output" role="dataout" width="512" />
  </interface>
  <interface name="address" kind="conduit" start="0">
   <property name="associatedClock" value="" />
   <property name="associatedReset" value="" />
   <property name="prSafe" value="false" />
   <port name="address" direction="input" role="address" width="14" />
  </interface>
  <interface name="clock" kind="clock" start="0">
   <property name="clockRate" value="0" />
   <property name="externallyDriven" value="false" />
   <property name="ptfSchematicName" value="" />
   <port name="clock" direction="input" role="clk" width="1" />
  </interface>
 </perimeter>
 <entity kind="weight_rom" version="1.0" name="weight_rom">
  <parameter name="AUTO_CLOCK_CLOCK_RATE" value="-1" />
  <parameter name="AUTO_CLOCK_CLOCK_DOMAIN" value="-1" />
  <parameter name="AUTO_CLOCK_RESET_DOMAIN" value="-1" />
  <parameter name="AUTO_GENERATION_ID" value="0" />
  <parameter name="AUTO_DEVICE" value="10AX066K3F40E2SG" />
  <parameter name="AUTO_DEVICE_FAMILY" value="Arria 10" />
  <parameter name="AUTO_UNIQUE_ID" value="" />
  <parameter name="AUTO_DEVICE_SPEEDGRADE" value="2" />
  <generatedFiles>
   <file
       path="/home/gtd/workspace/qts_prj/cnn/Mobilenet_FPGA_Accelarator_nios_ddr4/ip/init_para_rom/weight_rom/synth/weight_rom.v"
       attributes="CONTAINS_INLINE_CONFIGURATION" />
  </generatedFiles>
  <childGeneratedFiles>
   <file
       path="/home/gtd/workspace/qts_prj/cnn/Mobilenet_FPGA_Accelarator_nios_ddr4/ip/init_para_rom/weight_rom/synth/weight_rom.v"
       attributes="CONTAINS_INLINE_CONFIGURATION" />
  </childGeneratedFiles>
  <sourceFiles>
   <file
       path="/home/gtd/workspace/qts_prj/cnn/Mobilenet_FPGA_Accelarator_nios_ddr4/ip/init_para_rom/weight_rom.ip" />
  </sourceFiles>
  <childSourceFiles>
   <file
       path="/software/quartus/qts18.1pro/ip/altera/megafunctions/rom_1port/rom_1_port_hw.tcl" />
  </childSourceFiles>
  <messages>
   <message level="Info" culprit="weight_rom">"Generating: weight_rom"</message>
   <message level="Info" culprit="weight_rom">"Generating: weight_rom_rom_1port_181_rouiaua"</message>
  </messages>
 </entity>
 <entity
   kind="rom_1port"
   version="18.1"
   name="weight_rom_rom_1port_181_rouiaua">
  <parameter name="GUI_CLOCK_ENABLE_INPUT_A" value="false" />
  <parameter name="GUI_NUMWORDS_A" value="16384" />
  <parameter name="DEVICE_FAMILY" value="Arria 10" />
  <parameter name="GUI_RAM_BLOCK_TYPE" value="Auto" />
  <parameter name="GUI_SingleClock" value="0" />
  <parameter name="GUI_AclrAddr" value="false" />
  <parameter name="GUI_INIT_FILE_LAYOUT" value="PORT_A" />
  <parameter name="GUI_MAXIMUM_DEPTH" value="0" />
  <parameter name="GUI_RegOutput" value="true" />
  <parameter name="GUI_CLOCK_ENABLE_OUTPUT_A" value="false" />
  <parameter name="GUI_RESOURCE_USAGE" value="512 M20K" />
  <parameter name="GUI_rden" value="false" />
  <parameter name="GUI_JTAG_ID" value="NONE" />
  <parameter name="GUI_WIDTH_A" value="512" />
  <parameter name="GUI_FORCE_TO_ZERO" value="false" />
  <parameter
     name="GUI_MIFfilename"
     value="/home/gtd/workspace/qts_prj/cnn/Mobilenet_FPGA_Accelarator_nios_ddr4/rtl/16.ddr_para_init/parameter/weight_part1.mif" />
  <parameter name="GUI_RegAddr" value="true" />
  <parameter name="GUI_JTAG_ENABLED" value="true" />
  <parameter name="GUI_INIT_TO_SIM_X" value="false" />
  <parameter name="GUI_AclrOutput" value="false" />
  <parameter name="GUI_WIDTHAD_A" value="14" />
  <parameter name="GUI_ADDRESSSTALL_A" value="false" />
  <parameter name="GUI_FILE_REFERENCE" value="0" />
  <parameter name="GUI_TBENCH" value="false" />
  <parameter name="GUI_SclrOutput" value="false" />
  <parameter name="GUI_MODULE_NAME" value="altera_syncram" />
  <parameter name="GUI_BlankMemory" value="1" />
  <generatedFiles>
   <file
       path="/home/gtd/workspace/qts_prj/cnn/Mobilenet_FPGA_Accelarator_nios_ddr4/ip/init_para_rom/weight_rom/rom_1port_181/synth/weight_rom_rom_1port_181_rouiaua.v"
       attributes="" />
  </generatedFiles>
  <childGeneratedFiles>
   <file
       path="/home/gtd/workspace/qts_prj/cnn/Mobilenet_FPGA_Accelarator_nios_ddr4/ip/init_para_rom/weight_rom/rom_1port_181/synth/weight_rom_rom_1port_181_rouiaua.v"
       attributes="" />
  </childGeneratedFiles>
  <sourceFiles>
   <file
       path="/software/quartus/qts18.1pro/ip/altera/megafunctions/rom_1port/rom_1_port_hw.tcl" />
  </sourceFiles>
  <childSourceFiles/>
  <instantiator instantiator="weight_rom" as="rom_1port_0" />
  <messages>
   <message level="Info" culprit="weight_rom">"Generating: weight_rom_rom_1port_181_rouiaua"</message>
  </messages>
 </entity>
</deploy>
